cybhpt_full.cpython-314t-x86_64-linux-gnu.so
pybhpt/__init__.py
pybhpt/flux.py
pybhpt/geo.py
pybhpt/hertz.py
pybhpt/metric.py
pybhpt/radial.py
pybhpt/redshift.py
pybhpt/swsh.py
pybhpt/teuk.py
pybhpt.libs/libgomp-870cb1d0.so.1.0.0
pybhpt.libs/libgsl-70512a4e.so.28.0.0
pybhpt.libs/libgslcblas-faf0af50.so.0.0.0
pybhpt-0.9.10.dist-info/METADATA
pybhpt-0.9.10.dist-info/WHEEL
pybhpt-0.9.10.dist-info/RECORD
pybhpt-0.9.10.dist-info/licenses/LICENSE
