Metadata-Version: 2.2
Name: pybhpt
Version: 0.9.10
Summary: Black Hole Perturbation Theory and Self-Force Algorithms in Python
Author-Email: Zach Nasipak <znasipak@gmail.com>
License: GPL
Classifier: Programming Language :: Python :: 3
Classifier: Programming Language :: Cython
Classifier: Programming Language :: C++
Classifier: License :: OSI Approved :: GNU General Public License (GPL)
Classifier: Natural Language :: English
Project-URL: Github, https://github.com/znasipak/pybhpt
Project-URL: Bug Tracker, https://github.com/znasipak/pybhpt/issues
Requires-Python: >=3.8
Requires-Dist: numpy<=2.2
Requires-Dist: scipy
Provides-Extra: testing
Requires-Dist: pytest; extra == "testing"
Requires-Dist: pytest-cov; extra == "testing"
Provides-Extra: dev
Requires-Dist: matplotlib; extra == "dev"
Requires-Dist: jupyter; extra == "dev"
Requires-Dist: ipython; extra == "dev"
Requires-Dist: ipykernel; extra == "dev"
Provides-Extra: extended
Requires-Dist: pandas; extra == "extended"
Requires-Dist: spherical; extra == "extended"
Requires-Dist: tqdm; extra == "extended"
